{
  "id": "1774638896607_feedback-positive-fb-1774638895974-nrugr4",
  "namespace": "raw_history",
  "title": "feedback_positive_fb_1774638895974_nrugr4",
  "content": "{\"id\":\"fb_1774638895974_nrugr4\",\"signal\":\"positive\",\"context\":\"User prefers tabs\",\"lastAction\":null,\"whatWentWrong\":null,\"whatToChange\":null,\"whatWorked\":\"Switched to tabs\",\"reasoning\":null,\"visualEvidence\":null,\"tags\":[\"style\",\"formatting\",\"entity:Customer\"],\"skill\":null,\"rubric\":null,\"actionType\":\"store-learning\",\"actionReason\":null,\"timestamp\":\"2026-03-27T19:14:55.974Z\",\"richContext\":{\"domain\":\"general\",\"filePaths\":[],\"errorType\":null,\"outcomeCategory\":\"standard-success\"}}",
  "tags": [
    "style",
    "formatting",
    "entity:Customer"
  ],
  "source": "feedback-event",
  "ttl": null,
  "metadata": {
    "signal": "positive",
    "actionType": "store-learning"
  },
  "createdAt": "2026-03-27T19:14:56.607Z",
  "lastUsedAt": null
}
