{
  "id": "1774984509136_feedback-negative-fb-1774984508952-h9p2zk",
  "namespace": "raw_history",
  "title": "feedback_negative_fb_1774984508952_h9p2zk",
  "content": "{\"id\":\"fb_1774984508952_h9p2zk\",\"signal\":\"negative\",\"context\":\"Test dedup inline write\",\"lastAction\":null,\"whatWentWrong\":\"Something broke again\",\"whatToChange\":null,\"whatWorked\":null,\"reasoning\":null,\"visualEvidence\":null,\"tags\":[\"dedup-test\"],\"skill\":null,\"rubric\":null,\"actionType\":\"store-mistake\",\"actionReason\":null,\"timestamp\":\"2026-03-31T19:15:08.952Z\",\"richContext\":{\"domain\":\"testing\",\"filePaths\":[],\"errorType\":null,\"outcomeCategory\":\"standard-failure\"}}",
  "tags": [
    "dedup-test"
  ],
  "source": "feedback-event",
  "ttl": null,
  "metadata": {
    "signal": "negative",
    "actionType": "store-mistake"
  },
  "createdAt": "2026-03-31T19:15:09.136Z",
  "lastUsedAt": null
}
