{
  "id": "1774900401750_feedback-negative-fb-1774900401579-29q6kx",
  "namespace": "raw_history",
  "title": "feedback_negative_fb_1774900401579_29q6kx",
  "content": "{\"id\":\"fb_1774900401579_29q6kx\",\"signal\":\"negative\",\"context\":\"Pipeline integration test failure 3\",\"lastAction\":null,\"whatWentWrong\":\"Integration broke\",\"whatToChange\":null,\"whatWorked\":null,\"reasoning\":null,\"visualEvidence\":null,\"tags\":[\"pipeline-integration-test\"],\"skill\":null,\"rubric\":null,\"actionType\":\"store-mistake\",\"actionReason\":null,\"timestamp\":\"2026-03-30T19:53:21.579Z\",\"richContext\":{\"domain\":\"testing\",\"filePaths\":[],\"errorType\":null,\"outcomeCategory\":\"standard-failure\"}}",
  "tags": [
    "pipeline-integration-test"
  ],
  "source": "feedback-event",
  "ttl": null,
  "metadata": {
    "signal": "negative",
    "actionType": "store-mistake"
  },
  "createdAt": "2026-03-30T19:53:21.750Z",
  "lastUsedAt": null
}
