{
  "id": "1774147881881_feedback-positive-fb-1774147881875-v0purc",
  "namespace": "raw_history",
  "title": "feedback_positive_fb_1774147881875_v0purc",
  "content": "{\"id\":\"fb_1774147881875_v0purc\",\"signal\":\"positive\",\"context\":\"adapter proof harness\",\"lastAction\":null,\"whatWentWrong\":null,\"whatToChange\":null,\"whatWorked\":\"end-to-end verification flow\",\"reasoning\":null,\"visualEvidence\":null,\"tags\":[\"verification\",\"proof\",\"entity:Customer\"],\"skill\":null,\"rubric\":null,\"actionType\":\"store-learning\",\"actionReason\":null,\"timestamp\":\"2026-03-22T02:51:21.875Z\",\"richContext\":{\"domain\":\"general\",\"filePaths\":[],\"errorType\":null,\"outcomeCategory\":\"standard-success\"}}",
  "tags": [
    "verification",
    "proof",
    "entity:Customer"
  ],
  "source": "feedback-event",
  "ttl": null,
  "metadata": {
    "signal": "positive",
    "actionType": "store-learning"
  },
  "createdAt": "2026-03-22T02:51:21.881Z",
  "lastUsedAt": null
}
