{
  "id": "1774634024265_feedback-negative-fb-1774634022403-wj7xed",
  "namespace": "raw_history",
  "title": "feedback_negative_fb_1774634022403_wj7xed",
  "content": "{\"id\":\"fb_1774634022403_wj7xed\",\"signal\":\"negative\",\"context\":\"Gate \\\"push-without-thread-check\\\" blocked tool \\\"Bash\\\": Check PR review threads (reviewThreads first:50) before pushing. Use satisfy_gate('pr_threads_checked', 'evidence') to bypass.\",\"lastAction\":null,\"whatWentWrong\":null,\"whatToChange\":null,\"whatWorked\":null,\"reasoning\":null,\"visualEvidence\":null,\"tags\":[\"audit-trail\",\"auto-capture\",\"gate:push-without-thread-check\",\"gates-engine\"],\"skill\":null,\"rubric\":null,\"actionType\":\"store-mistake\",\"actionReason\":null,\"timestamp\":\"2026-03-27T17:53:42.403Z\",\"richContext\":{\"domain\":\"general\",\"filePaths\":[],\"errorType\":null,\"outcomeCategory\":\"standard-failure\"}}",
  "tags": [
    "audit-trail",
    "auto-capture",
    "gate:push-without-thread-check",
    "gates-engine"
  ],
  "source": "feedback-event",
  "ttl": null,
  "metadata": {
    "signal": "negative",
    "actionType": "store-mistake"
  },
  "createdAt": "2026-03-27T17:53:44.265Z",
  "lastUsedAt": null
}
