{
  "id": "1774647065467_feedback-negative-fb-1774647065273-60s2uy",
  "namespace": "raw_history",
  "title": "feedback_negative_fb_1774647065273_60s2uy",
  "content": "{\"id\":\"fb_1774647065273_60s2uy\",\"signal\":\"negative\",\"context\":\"Actually I hate tabs now\",\"lastAction\":null,\"whatWentWrong\":\"User asked for spaces\",\"whatToChange\":null,\"whatWorked\":null,\"reasoning\":null,\"visualEvidence\":null,\"tags\":[\"style\"],\"skill\":null,\"rubric\":null,\"actionType\":\"store-mistake\",\"actionReason\":null,\"timestamp\":\"2026-03-27T21:31:05.273Z\",\"richContext\":{\"domain\":\"general\",\"filePaths\":[],\"errorType\":null,\"outcomeCategory\":\"standard-failure\"}}",
  "tags": [
    "style"
  ],
  "source": "feedback-event",
  "ttl": null,
  "metadata": {
    "signal": "negative",
    "actionType": "store-mistake"
  },
  "createdAt": "2026-03-27T21:31:05.467Z",
  "lastUsedAt": null
}
