{
  "id": "1774572012004_feedback-positive-fb-1774572011653-z7otni",
  "namespace": "raw_history",
  "title": "feedback_positive_fb_1774572011653_z7otni",
  "content": "{\"id\":\"fb_1774572011653_z7otni\",\"signal\":\"positive\",\"context\":\"good work\",\"lastAction\":null,\"whatWentWrong\":null,\"whatToChange\":null,\"whatWorked\":\"evidence-based approach\",\"reasoning\":null,\"visualEvidence\":null,\"tags\":[\"test-no-attribution\"],\"skill\":null,\"rubric\":null,\"actionType\":\"store-learning\",\"actionReason\":null,\"timestamp\":\"2026-03-27T00:40:11.653Z\",\"richContext\":{\"domain\":\"general\",\"filePaths\":[],\"errorType\":null,\"outcomeCategory\":\"standard-success\"}}",
  "tags": [
    "test-no-attribution"
  ],
  "source": "feedback-event",
  "ttl": null,
  "metadata": {
    "signal": "positive",
    "actionType": "store-learning"
  },
  "createdAt": "2026-03-27T00:40:12.004Z",
  "lastUsedAt": null
}
