{
  "id": "1774646883321_feedback-positive-fb-1774646882366-lf5pk1",
  "namespace": "raw_history",
  "title": "feedback_positive_fb_1774646882366_lf5pk1",
  "content": "{\"id\":\"fb_1774646882366_lf5pk1\",\"signal\":\"positive\",\"context\":\"Job limit-test-1 passed verification after 1 attempt(s)\",\"lastAction\":null,\"whatWentWrong\":null,\"whatToChange\":null,\"whatWorked\":\"Verification loop accepted output\",\"reasoning\":null,\"visualEvidence\":null,\"tags\":[\"verification-loop\"],\"skill\":\"async-job-runner\",\"rubric\":null,\"actionType\":\"store-learning\",\"actionReason\":null,\"timestamp\":\"2026-03-27T21:28:02.366Z\",\"richContext\":{\"domain\":\"testing\",\"filePaths\":[],\"errorType\":null,\"outcomeCategory\":\"standard-success\"}}",
  "tags": [
    "verification-loop"
  ],
  "source": "feedback-event",
  "ttl": null,
  "metadata": {
    "signal": "positive",
    "actionType": "store-learning"
  },
  "createdAt": "2026-03-27T21:28:03.321Z",
  "lastUsedAt": null
}
