{
  "id": "1774886483881_feedback-negative-fb-1774886481270-28er7a",
  "namespace": "raw_history",
  "title": "feedback_negative_fb_1774886481270_28er7a",
  "content": "{\"id\":\"fb_1774886481270_28er7a\",\"signal\":\"negative\",\"context\":\"Gate \\\"protected-branch-push\\\" blocked tool \\\"Bash\\\": Direct push to protected branch. Use feature branches and PRs.\",\"lastAction\":null,\"whatWentWrong\":null,\"whatToChange\":null,\"whatWorked\":null,\"reasoning\":null,\"visualEvidence\":null,\"tags\":[\"audit-trail\",\"auto-capture\",\"gate:protected-branch-push\",\"gates-engine\",\"entity:Customer\"],\"skill\":null,\"rubric\":null,\"actionType\":\"store-mistake\",\"actionReason\":null,\"timestamp\":\"2026-03-30T16:01:21.270Z\",\"richContext\":{\"domain\":\"general\",\"filePaths\":[],\"errorType\":null,\"outcomeCategory\":\"standard-failure\"}}",
  "tags": [
    "audit-trail",
    "auto-capture",
    "gate:protected-branch-push",
    "gates-engine",
    "entity:Customer"
  ],
  "source": "feedback-event",
  "ttl": null,
  "metadata": {
    "signal": "negative",
    "actionType": "store-mistake"
  },
  "createdAt": "2026-03-30T16:01:23.881Z",
  "lastUsedAt": null
}
