{
  "id": "1774646920415_feedback-positive-fb-1774646919121-dczky0",
  "namespace": "raw_history",
  "title": "feedback_positive_fb_1774646919121_dczky0",
  "content": "{\"id\":\"fb_1774646919121_dczky0\",\"signal\":\"positive\",\"context\":\"test context for ML verification\",\"lastAction\":null,\"whatWentWrong\":null,\"whatToChange\":null,\"whatWorked\":\"the feature worked correctly\",\"reasoning\":null,\"visualEvidence\":null,\"tags\":[\"testing\"],\"skill\":null,\"rubric\":null,\"actionType\":\"store-learning\",\"actionReason\":null,\"timestamp\":\"2026-03-27T21:28:39.121Z\",\"richContext\":{\"domain\":\"testing\",\"filePaths\":[],\"errorType\":null,\"outcomeCategory\":\"standard-success\"}}",
  "tags": [
    "testing"
  ],
  "source": "feedback-event",
  "ttl": null,
  "metadata": {
    "signal": "positive",
    "actionType": "store-learning"
  },
  "createdAt": "2026-03-27T21:28:40.415Z",
  "lastUsedAt": null
}
