{
  "id": "1774975410773_feedback-negative-fb-1774975409780-8bc6zr",
  "namespace": "raw_history",
  "title": "feedback_negative_fb_1774975409780_8bc6zr",
  "content": "{\"id\":\"fb_1774975409780_8bc6zr\",\"signal\":\"negative\",\"context\":\"Pipeline integration test failure 0\",\"lastAction\":null,\"whatWentWrong\":\"Integration broke\",\"whatToChange\":null,\"whatWorked\":null,\"reasoning\":null,\"visualEvidence\":null,\"tags\":[\"pipeline-integration-test\"],\"skill\":null,\"rubric\":null,\"actionType\":\"store-mistake\",\"actionReason\":null,\"timestamp\":\"2026-03-31T16:43:29.780Z\",\"richContext\":{\"domain\":\"testing\",\"filePaths\":[],\"errorType\":null,\"outcomeCategory\":\"standard-failure\"}}",
  "tags": [
    "pipeline-integration-test"
  ],
  "source": "feedback-event",
  "ttl": null,
  "metadata": {
    "signal": "negative",
    "actionType": "store-mistake"
  },
  "createdAt": "2026-03-31T16:43:30.773Z",
  "lastUsedAt": null
}
