{
  "id": "1774972562584_feedback-positive-fb-1774972561962-4mz9j9",
  "namespace": "raw_history",
  "title": "feedback_positive_fb_1774972561962_4mz9j9",
  "content": "{\"id\":\"fb_1774972561962_4mz9j9\",\"signal\":\"positive\",\"context\":\"test context for ML verification call 0\",\"lastAction\":null,\"whatWentWrong\":null,\"whatToChange\":null,\"whatWorked\":\"the feature worked correctly\",\"reasoning\":null,\"visualEvidence\":null,\"tags\":[\"testing\"],\"skill\":null,\"rubric\":null,\"actionType\":\"store-learning\",\"actionReason\":null,\"timestamp\":\"2026-03-31T15:56:01.962Z\",\"richContext\":{\"domain\":\"testing\",\"filePaths\":[],\"errorType\":null,\"outcomeCategory\":\"standard-success\"}}",
  "tags": [
    "testing"
  ],
  "source": "feedback-event",
  "ttl": null,
  "metadata": {
    "signal": "positive",
    "actionType": "store-learning"
  },
  "createdAt": "2026-03-31T15:56:02.584Z",
  "lastUsedAt": null
}
