{
  "id": "1774874824064_feedback-positive-fb-1774874823732-3005az",
  "namespace": "raw_history",
  "title": "feedback_positive_fb_1774874823732_3005az",
  "content": "{\"id\":\"fb_1774874823732_3005az\",\"signal\":\"positive\",\"context\":\"first entry\",\"lastAction\":null,\"whatWentWrong\":null,\"whatToChange\":null,\"whatWorked\":\"worked well\",\"reasoning\":null,\"visualEvidence\":null,\"tags\":[\"testing\",\"watcher-ingested\",\"bridged-from:amp-plugin-bridge\"],\"skill\":null,\"rubric\":null,\"actionType\":\"store-learning\",\"actionReason\":null,\"timestamp\":\"2026-03-30T12:47:03.732Z\",\"richContext\":{\"domain\":\"testing\",\"filePaths\":[],\"errorType\":null,\"outcomeCategory\":\"standard-success\"}}",
  "tags": [
    "testing",
    "watcher-ingested",
    "bridged-from:amp-plugin-bridge"
  ],
  "source": "feedback-event",
  "ttl": null,
  "metadata": {
    "signal": "positive",
    "actionType": "store-learning"
  },
  "createdAt": "2026-03-30T12:47:04.064Z",
  "lastUsedAt": null
}
