{
  "id": "1774902102770_feedback-positive-fb-1774902102523-tm0ufa",
  "namespace": "raw_history",
  "title": "feedback_positive_fb_1774902102523_tm0ufa",
  "content": "{\"id\":\"fb_1774902102523_tm0ufa\",\"signal\":\"positive\",\"context\":\"unit tests added for edge cases\",\"lastAction\":null,\"whatWentWrong\":null,\"whatToChange\":null,\"whatWorked\":null,\"reasoning\":null,\"visualEvidence\":null,\"tags\":[\"testing\"],\"skill\":null,\"rubric\":null,\"actionType\":\"store-learning\",\"actionReason\":null,\"timestamp\":\"2026-03-30T20:21:42.523Z\",\"richContext\":{\"domain\":\"testing\",\"filePaths\":[\"src/api.js\"],\"errorType\":null,\"outcomeCategory\":\"standard-success\"}}",
  "tags": [
    "testing"
  ],
  "source": "feedback-event",
  "ttl": null,
  "metadata": {
    "signal": "positive",
    "actionType": "store-learning"
  },
  "createdAt": "2026-03-30T20:21:42.770Z",
  "lastUsedAt": null
}
