{
  "id": "1774975371527_feedback-positive-fb-1774975370966-dj8w5j",
  "namespace": "raw_history",
  "title": "feedback_positive_fb_1774975370966_dj8w5j",
  "content": "{\"id\":\"fb_1774975370966_dj8w5j\",\"signal\":\"positive\",\"context\":\"unit tests added for edge cases\",\"lastAction\":null,\"whatWentWrong\":null,\"whatToChange\":null,\"whatWorked\":null,\"reasoning\":null,\"visualEvidence\":null,\"tags\":[\"testing\"],\"skill\":null,\"rubric\":null,\"actionType\":\"store-learning\",\"actionReason\":null,\"timestamp\":\"2026-03-31T16:42:50.966Z\",\"richContext\":{\"domain\":\"testing\",\"filePaths\":[\"src/api.js\"],\"errorType\":null,\"outcomeCategory\":\"standard-success\"}}",
  "tags": [
    "testing"
  ],
  "source": "feedback-event",
  "ttl": null,
  "metadata": {
    "signal": "positive",
    "actionType": "store-learning"
  },
  "createdAt": "2026-03-31T16:42:51.527Z",
  "lastUsedAt": null
}
