{
  "id": "1775058962458_feedback-positive-fb-1775058962424-yk5o5j",
  "namespace": "raw_history",
  "title": "feedback_positive_fb_1775058962424_yk5o5j",
  "content": "{\"id\":\"fb_1775058962424_yk5o5j\",\"signal\":\"positive\",\"context\":\"test context for ML verification\",\"lastAction\":null,\"whatWentWrong\":null,\"whatToChange\":null,\"whatWorked\":\"the feature worked correctly\",\"reasoning\":null,\"visualEvidence\":null,\"tags\":[\"testing\"],\"skill\":null,\"rubric\":null,\"actionType\":\"store-learning\",\"actionReason\":null,\"timestamp\":\"2026-04-01T15:56:02.424Z\",\"richContext\":{\"domain\":\"testing\",\"filePaths\":[],\"errorType\":null,\"outcomeCategory\":\"standard-success\"}}",
  "tags": [
    "testing"
  ],
  "source": "feedback-event",
  "ttl": null,
  "metadata": {
    "signal": "positive",
    "actionType": "store-learning"
  },
  "createdAt": "2026-04-01T15:56:02.458Z",
  "lastUsedAt": null
}
