{
  "id": "1775134372306_feedback-positive-fb-1775134372147-5olr38",
  "namespace": "raw_history",
  "title": "feedback_positive_fb_1775134372147_5olr38",
  "content": "{\"id\":\"fb_1775134372147_5olr38\",\"signal\":\"positive\",\"context\":\"Job managed-job passed verification after 1 attempt(s)\",\"relatedFeedbackId\":null,\"lastAction\":null,\"whatWentWrong\":null,\"whatToChange\":null,\"whatWorked\":\"Verification loop accepted output\",\"reasoning\":null,\"visualEvidence\":null,\"tags\":[\"testing\",\"verification-loop\"],\"skill\":\"async-job-runner\",\"failureType\":null,\"rubric\":null,\"actionType\":\"store-learning\",\"actionReason\":null,\"timestamp\":\"2026-04-02T12:52:52.147Z\",\"richContext\":{\"domain\":\"testing\",\"filePaths\":[],\"errorType\":null,\"outcomeCategory\":\"standard-success\"}}",
  "tags": [
    "testing",
    "verification-loop"
  ],
  "source": "feedback-event",
  "ttl": null,
  "metadata": {
    "signal": "positive",
    "actionType": "store-learning"
  },
  "createdAt": "2026-04-02T12:52:52.306Z",
  "lastUsedAt": null
}
