{
  "id": "1775058840299_feedback-positive-fb-1775058840076-8svqdg",
  "namespace": "raw_history",
  "title": "feedback_positive_fb_1775058840076_8svqdg",
  "content": "{\"id\":\"fb_1775058840076_8svqdg\",\"signal\":\"positive\",\"context\":\"Job managed-job passed verification after 1 attempt(s)\",\"lastAction\":null,\"whatWentWrong\":null,\"whatToChange\":null,\"whatWorked\":\"Verification loop accepted output\",\"reasoning\":null,\"visualEvidence\":null,\"tags\":[\"testing\",\"verification-loop\"],\"skill\":\"async-job-runner\",\"rubric\":null,\"actionType\":\"store-learning\",\"actionReason\":null,\"timestamp\":\"2026-04-01T15:54:00.076Z\",\"richContext\":{\"domain\":\"testing\",\"filePaths\":[],\"errorType\":null,\"outcomeCategory\":\"standard-success\"}}",
  "tags": [
    "testing",
    "verification-loop"
  ],
  "source": "feedback-event",
  "ttl": null,
  "metadata": {
    "signal": "positive",
    "actionType": "store-learning"
  },
  "createdAt": "2026-04-01T15:54:00.299Z",
  "lastUsedAt": null
}
