{
  "id": "1775054725082_feedback-positive-fb-1775054723262-aurfef",
  "namespace": "raw_history",
  "title": "feedback_positive_fb_1775054723262_aurfef",
  "content": "{\"id\":\"fb_1775054723262_aurfef\",\"signal\":\"positive\",\"context\":\"test context for ML verification\",\"lastAction\":null,\"whatWentWrong\":null,\"whatToChange\":null,\"whatWorked\":\"the feature worked correctly\",\"reasoning\":null,\"visualEvidence\":null,\"tags\":[\"testing\"],\"skill\":null,\"rubric\":null,\"actionType\":\"store-learning\",\"actionReason\":null,\"timestamp\":\"2026-04-01T14:45:23.262Z\",\"richContext\":{\"domain\":\"testing\",\"filePaths\":[],\"errorType\":null,\"outcomeCategory\":\"standard-success\"}}",
  "tags": [
    "testing"
  ],
  "source": "feedback-event",
  "ttl": null,
  "metadata": {
    "signal": "positive",
    "actionType": "store-learning"
  },
  "createdAt": "2026-04-01T14:45:25.082Z",
  "lastUsedAt": null
}
