{
  "id": "1775066481427_feedback-positive-fb-1775066481334-ja0noa",
  "namespace": "raw_history",
  "title": "feedback_positive_fb_1775066481334_ja0noa",
  "content": "{\"id\":\"fb_1775066481334_ja0noa\",\"signal\":\"positive\",\"context\":\"Job pause-job passed verification after 1 attempt(s)\",\"lastAction\":null,\"whatWentWrong\":null,\"whatToChange\":null,\"whatWorked\":\"Verification loop accepted output\",\"reasoning\":null,\"visualEvidence\":null,\"tags\":[\"runtime\",\"verification-loop\"],\"skill\":\"async-job-runner\",\"rubric\":null,\"actionType\":\"store-learning\",\"actionReason\":null,\"timestamp\":\"2026-04-01T18:01:21.334Z\",\"richContext\":{\"domain\":\"general\",\"filePaths\":[],\"errorType\":null,\"outcomeCategory\":\"standard-success\"}}",
  "tags": [
    "runtime",
    "verification-loop"
  ],
  "source": "feedback-event",
  "ttl": null,
  "metadata": {
    "signal": "positive",
    "actionType": "store-learning"
  },
  "createdAt": "2026-04-01T18:01:21.427Z",
  "lastUsedAt": null
}
