{
  "id": "1775141789393_feedback-positive-fb-1775141789318-6tokst",
  "namespace": "raw_history",
  "title": "feedback_positive_fb_1775141789318_6tokst",
  "content": "{\"id\":\"fb_1775141789318_6tokst\",\"signal\":\"positive\",\"context\":\"adapter proof harness\",\"relatedFeedbackId\":null,\"lastAction\":null,\"whatWentWrong\":null,\"whatToChange\":null,\"whatWorked\":\"end-to-end verification flow\",\"reasoning\":null,\"visualEvidence\":null,\"tags\":[\"verification\",\"proof\",\"entity:Customer\"],\"skill\":null,\"failureType\":null,\"rubric\":null,\"actionType\":\"store-learning\",\"actionReason\":null,\"timestamp\":\"2026-04-02T14:56:29.318Z\",\"richContext\":{\"domain\":\"general\",\"filePaths\":[],\"errorType\":null,\"outcomeCategory\":\"standard-success\"}}",
  "tags": [
    "verification",
    "proof",
    "entity:Customer"
  ],
  "source": "feedback-event",
  "ttl": null,
  "metadata": {
    "signal": "positive",
    "actionType": "store-learning"
  },
  "createdAt": "2026-04-02T14:56:29.393Z",
  "lastUsedAt": null
}
