{
  "id": "1775249195532_feedback-positive-fb-1775249195158-czuxfo",
  "namespace": "raw_history",
  "title": "feedback_positive_fb_1775249195158_czuxfo",
  "content": "{\"id\":\"fb_1775249195158_czuxfo\",\"signal\":\"positive\",\"context\":\"Job batch-2 passed verification after 1 attempt(s)\",\"submittedContext\":\"Job batch-2 passed verification after 1 attempt(s)\",\"relatedFeedbackId\":null,\"lastAction\":null,\"whatWentWrong\":null,\"whatToChange\":null,\"whatWorked\":\"Verification loop accepted output\",\"reasoning\":null,\"visualEvidence\":null,\"conversationWindow\":null,\"distillation\":null,\"tags\":[\"ops\",\"verification-loop\"],\"skill\":\"async-job-runner\",\"failureType\":null,\"rubric\":null,\"actionType\":\"store-learning\",\"actionReason\":null,\"structuredRule\":null,\"timestamp\":\"2026-04-03T20:46:35.158Z\",\"richContext\":{\"domain\":\"general\",\"filePaths\":[],\"errorType\":null,\"outcomeCategory\":\"standard-success\"}}",
  "tags": [
    "ops",
    "verification-loop"
  ],
  "source": "feedback-event",
  "ttl": null,
  "metadata": {
    "signal": "positive",
    "actionType": "store-learning"
  },
  "createdAt": "2026-04-03T20:46:35.532Z",
  "lastUsedAt": null
}
