{
  "id": "1775143370157_feedback-positive-fb-1775143370005-d65dmf",
  "namespace": "raw_history",
  "title": "feedback_positive_fb_1775143370005_d65dmf",
  "content": "{\"id\":\"fb_1775143370005_d65dmf\",\"signal\":\"positive\",\"context\":\"Job pause-job passed verification after 1 attempt(s)\",\"relatedFeedbackId\":null,\"lastAction\":null,\"whatWentWrong\":null,\"whatToChange\":null,\"whatWorked\":\"Verification loop accepted output\",\"reasoning\":null,\"visualEvidence\":null,\"tags\":[\"runtime\",\"verification-loop\"],\"skill\":\"async-job-runner\",\"failureType\":null,\"rubric\":null,\"actionType\":\"store-learning\",\"actionReason\":null,\"timestamp\":\"2026-04-02T15:22:50.005Z\",\"richContext\":{\"domain\":\"general\",\"filePaths\":[],\"errorType\":null,\"outcomeCategory\":\"standard-success\"}}",
  "tags": [
    "runtime",
    "verification-loop"
  ],
  "source": "feedback-event",
  "ttl": null,
  "metadata": {
    "signal": "positive",
    "actionType": "store-learning"
  },
  "createdAt": "2026-04-02T15:22:50.157Z",
  "lastUsedAt": null
}
