{
  "id": "1775224121753_feedback-negative-fb-1775224121613-citej3",
  "namespace": "raw_history",
  "title": "feedback_negative_fb_1775224121613_citej3",
  "content": "{\"id\":\"fb_1775224121613_citej3\",\"signal\":\"negative\",\"context\":\"test from verification\",\"submittedContext\":\"test from verification\",\"relatedFeedbackId\":null,\"lastAction\":null,\"whatWentWrong\":\"test from verification\",\"whatToChange\":null,\"whatWorked\":null,\"reasoning\":null,\"visualEvidence\":null,\"conversationWindow\":null,\"distillation\":null,\"tags\":[\"cli-feedback\",\"negative\"],\"skill\":null,\"failureType\":null,\"rubric\":null,\"actionType\":\"store-mistake\",\"actionReason\":null,\"timestamp\":\"2026-04-03T13:48:41.613Z\",\"richContext\":{\"domain\":\"testing\",\"filePaths\":[],\"errorType\":null,\"outcomeCategory\":\"standard-failure\"}}",
  "tags": [
    "cli-feedback",
    "negative"
  ],
  "source": "feedback-event",
  "ttl": null,
  "metadata": {
    "signal": "negative",
    "actionType": "store-mistake"
  },
  "createdAt": "2026-04-03T13:48:41.753Z",
  "lastUsedAt": null
}
