{
  "id": "1775065868900_feedback-positive-fb-1775065868665-gtug78",
  "namespace": "raw_history",
  "title": "feedback_positive_fb_1775065868665_gtug78",
  "content": "{\"id\":\"fb_1775065868665_gtug78\",\"signal\":\"positive\",\"context\":\"Job batch-2 passed verification after 1 attempt(s)\",\"lastAction\":null,\"whatWentWrong\":null,\"whatToChange\":null,\"whatWorked\":\"Verification loop accepted output\",\"reasoning\":null,\"visualEvidence\":null,\"tags\":[\"ops\",\"verification-loop\"],\"skill\":\"async-job-runner\",\"rubric\":null,\"actionType\":\"store-learning\",\"actionReason\":null,\"timestamp\":\"2026-04-01T17:51:08.665Z\",\"richContext\":{\"domain\":\"general\",\"filePaths\":[],\"errorType\":null,\"outcomeCategory\":\"standard-success\"}}",
  "tags": [
    "ops",
    "verification-loop"
  ],
  "source": "feedback-event",
  "ttl": null,
  "metadata": {
    "signal": "positive",
    "actionType": "store-learning"
  },
  "createdAt": "2026-04-01T17:51:08.900Z",
  "lastUsedAt": null
}
